cli/__init__.py
cli/cli_mmanager.py
core/__init__.py
core/cipher.py
storage/__init__.py
storage/aws_storage.py
storage/base_provider.py
storage/storage_factory.py
storage/vault_storage.py
secure_test_automation-1.3.1.dist-info/LICENSE
secure_test_automation-1.3.1.dist-info/METADATA
secure_test_automation-1.3.1.dist-info/WHEEL
secure_test_automation-1.3.1.dist-info/entry_points.txt
secure_test_automation-1.3.1.dist-info/RECORD
