Metadata-Version: 2.3
Name: secure-test-automation
Version: 1.3.1
Summary: Crypto tool for automation frameworks
Home-page: https://github.com/dmberezovskyii/secure-test-automation
License: MIT
Keywords: cryptography,Selenum,appium,secrets,security
Author: Dmytro Berezovskyi
Author-email: dmberezovskyi@gmail.com
Requires-Python: >=3.10,<4.0
Classifier: License :: OSI Approved :: MIT License
Classifier: Programming Language :: Python :: 3
Classifier: Programming Language :: Python :: 3.10
Classifier: Programming Language :: Python :: 3.11
Classifier: Programming Language :: Python :: 3.12
Classifier: Programming Language :: Python :: 3.13
Provides-Extra: docs
Requires-Dist: PyYAML (==6.0.2)
Requires-Dist: boto3 (>=1.35.92,<2.0.0)
Requires-Dist: click (>=8.1.8,<9.0.0)
Requires-Dist: cryptography (==44.0.0)
Requires-Dist: hvac (>=2.3.0,<3.0.0)
Requires-Dist: pydantic (>=2.10.3,<3.0.0)
Requires-Dist: pyfiglet (==1.0.2)
Requires-Dist: pytest (==8.3.2)
Requires-Dist: pytest-html (==4.1.1)
Requires-Dist: sphinx (>=8.1.3,<9.0.0) ; extra == "docs"
Requires-Dist: sphinx_rtd_theme (>=3.0.2,<4.0.0) ; extra == "docs"
Requires-Dist: toml (==0.10.2)
Project-URL: Repository, https://github.com/dmberezovskyii/secure-test-automation
